UseData: False
BuildSelection: Cycle

BuildChoices:
  Zerg:
    BotName: ManifestorBot
    Cycle:
      - StandardOpener
      - EarlyAggression
      - TurtleEco

  Terran:
    BotName: ManifestorBot
    Cycle:
      - StandardOpener

  Protoss:
    BotName: ManifestorBot
    Cycle:
      - StandardOpener

  Random:
    BotName: ManifestorBot
    Cycle:
      - StandardOpener


Builds:

  StandardOpener:
    ConstantWorkerProductionTill: 20
    OpeningBuildOrder:
      - 13 overlord
      - 16 hatchery @ nat
      - 18 extractor
      - 17 spawningpool
      - 19 overlord
      - 20 queen
      - 20 queen
      - 22 zergling x4
      - 100 zerglingmovementspeed


  EarlyAggression:
    ConstantWorkerProductionTill: 16
    OpeningBuildOrder:
      - 13 overlord
      - 12 spawningpool
      - 14 extractor
      - 14 queen
      - 15 zergling x6
      - 16 overlord
      - 17 zergling x6
      - 18 expand @ nat
      - 100 zerglingmovementspeed


  TurtleEco:
    ConstantWorkerProductionTill: 24
    OpeningBuildOrder:
      - 13 overlord
      - 16 hatchery @ nat
      - 18 spawningpool
      - 19 overlord
      - 20 queen
      - 20 queen
      - 22 hatchery
      - 24 extractor
      - 26 overlord
      - 28 roachwarren